{"type":"header","name":"t:sections.header.name","sections":{"announcement_bar_header_xkM3UK":{"type":"announcement-bar-header","blocks":{"announcement_czN3JV":{"type":"announcement","settings":{"text":"FREE shipping for orders over R1300! Ts & Cs apply.","link_name":"","link_url":"","color_background":"rgba(0,0,0,0)","color_text":"rgba(0,0,0,0)","color_link":"rgba(0,0,0,0)"}},"announcement_QTVALV":{"type":"announcement","settings":{"text":"NEW Improved Online Store","link_name":"","link_url":"","color_background":"rgba(0,0,0,0)","color_text":"rgba(0,0,0,0)","color_link":"rgba(0,0,0,0)"}},"announcement_pPpJEe":{"type":"announcement","settings":{"text":"FREE shipping for BobBox orders over R500! Ts & Cs apply.","link_name":"","link_url":"","color_background":"rgba(0,0,0,0)","color_text":"rgba(0,0,0,0)","color_link":"rgba(0,0,0,0)"}}},"block_order":["announcement_czN3JV","announcement_QTVALV","announcement_pPpJEe"],"settings":{"width":"page-fullwidth","text_size":"announcement-text-5","slider_mode":true,"bar_time":3}},"header":{"type":"header","blocks":{"a09f6cc1-7be6-4132-816c-cc67060d5f8e":{"type":"main_menu_icons","settings":{"icon1":"dog_sm","icon2":"cat_sm","icon3":"fish_sm","icon4":"bird_sm","icon5":"horse_sm","icon6":"hotel_sm","icon7":"hotel_sm","icon8":"pharmacy_sm","icon9":"hotel_sm","icon10":"sale_sm","icon11":"new_sm"}},"mega_menu_Ba947c":{"type":"mega_menu","settings":{"mega_menu_item_name":"Dogs","grid":"col-one_fifth","show_banner":false,"banner_link":"shopify:\/\/collections\/dogs","heading":"","text":"","button_label":""}},"mega_menu_tfA4DY":{"type":"mega_menu","settings":{"mega_menu_item_name":"Cats","grid":"col-one_fifth","show_banner":false,"banner_link":"","heading":"Free Shipping","text":"No code needed, just head for checkout!","button_label":"Shop Now!"}},"6ff79c47-1cd4-42b8-a54e-7e942f400a12":{"type":"mega_menu","settings":{"mega_menu_item_name":"Default","grid":"col-3","show_banner":true,"banner_link":"","heading":"Free Shipping","text":"No code needed, just head for checkout!","button_label":"Shop Now!"}},"1bac9096-6d19-4857-9b37-e562cd6d91d9":{"type":"phone","disabled":true,"settings":{"icon_1":"phone_sm","phone_1":"+27 XXX XXX XXXX","phone_1_as_link":true,"icon_2":"","phone_2":"","phone_2_as_link":true,"info_text_size":"body3","info":"Your number phone","icons_color":"rgba(0,0,0,0)","text_color":"rgba(0,0,0,0)"}},"badges_R3VjCY":{"type":"badges","settings":{"badge_items_1":"","badge_text_1":"Sale","badge_color_1":"rgba(0,0,0,0)","badge_items_2":"","badge_text_2":"Popular","badge_color_2":"rgba(0,0,0,0)","badge_items_3":"","badge_text_3":"Popular","badge_color_3":"rgba(0,0,0,0)","badge_items_4":"","badge_text_4":"Popular","badge_color_4":"rgba(0,0,0,0)","badge_items_5":"","badge_text_5":"Popular","badge_color_5":"rgba(0,0,0,0)"}}},"block_order":["a09f6cc1-7be6-4132-816c-cc67060d5f8e","mega_menu_Ba947c","mega_menu_tfA4DY","6ff79c47-1cd4-42b8-a54e-7e942f400a12","1bac9096-6d19-4857-9b37-e562cd6d91d9","badges_R3VjCY"],"custom_css":[],"settings":{"header_layout":"header-layout-vertical","menu":"main-menu","secondary_menu":"secondary-menu","width":"default","show_search":true,"open_search":true,"enable_sticky_header":true,"show_color_line":true,"menu_font_weight":"font-weight-normal","icons_color":"#82a3b9","logo":"shopify:\/\/shop_images\/LaBrie_Logo_White.svg","logo_svg":"","logo_max_width":210,"logo_position":"left","logo_svg_mobile":"","logo_max_width_mobile":150,"logo_position_mobile":"center","show_menu_animation_tiles":true,"visible_items_count":10,"icons_size":20,"color_tile_base":"#f6f7fa","color_tile_active":"rgba(0,0,0,0)","show_menu_animation_vertical":true,"vertical_menu_item_padding":12,"color_button":"rgba(0,0,0,0)","sections_count":"1"}}},"order":["announcement_bar_header_xkM3UK","header"]}